poker_stats/__init__.py
poker_stats/__main__.py
poker_stats/api.py
poker_stats/config.py
poker_stats/entity.py
poker_stats/hand_filter.py
poker_stats/hand_parser.py
poker_stats/report.py
poker_stats/report_printer.py
poker_stats/ver.py
poker_stats-0.5.0.dist-info/METADATA
poker_stats-0.5.0.dist-info/WHEEL
poker_stats-0.5.0.dist-info/entry_points.txt
poker_stats-0.5.0.dist-info/top_level.txt
poker_stats-0.5.0.dist-info/RECORD
